{
	"geode": "2.0.0-beta.24",
	"gd": {
		"win": "2.204"
	},
	"version": "v2.3.0",
	"id": "prevter.openhack",
	"name": "OpenHack",
	"developer": "Prevter",
	"description": "A collection of hacks for Geometry Dash",
	"tags": [
		"Universal",
		"Gameplay",
		"Cheats"
	],
	"repository": "https://github.com/Prevter/GDOpenHack",
	"issues": {
		"info": "Join the Discord server for support",
		"url": "https://discord.gg/HaHn7RSJ4Q"
	},
	"resources": {
		"sprites": [
			"screenshot-res.png"
		],
		"files": [
			"resources/fonts/*",
			"resources/hacks/*",
			"resources/licenses/*"
		]
	},
	"early-load": true,
	"api": {
		"include": [
			"api/*.hpp"
		]
	},
	"settings": {
		"legacy-render": {
			"name": "Use Legacy rendering",
			"description": "Use OpenGL 2.0 instead of OpenGL 3.0 for rendering, which can solve some rendering issues on older hardware",
			"type": "bool",
			"default": false
		}
	}
}